<?xml version="1.0" encoding="utf-8"?>
<savedqueries xmlns:xsi="http://www.w3.org/2001/XMLSchema-instance">
  <savedquery>
    <IsCustomizable>1</IsCustomizable>
    <CanBeDeleted>0</CanBeDeleted>
    <isquickfindquery>0</isquickfindquery>
    <isprivate>0</isprivate>
    <isdefault>1</isdefault>
    <savedqueryid>{0031f132-68c8-455a-a3eb-c8b687264d8a}</savedqueryid>
    <layoutxml>
      <grid name="mzh_assignees" jump="mzh_assigneename" select="1" icon="1" preview="0">
        <row name="mzh_assignee" id="mzh_assigneeid">
          <cell name="mzh_assigneename" width="300" />
          <cell name="createdon" width="125" />
        </row>
      </grid>
    </layoutxml>
    <querytype>64</querytype>
    <fetchxml>
      <fetch version="1.0" mapping="logical">
        <entity name="mzh_assignee">
          <attribute name="mzh_assigneeid" />
          <attribute name="mzh_assigneename" />
          <attribute name="createdon" />
          <filter type="and">
            <condition attribute="statecode" operator="eq" value="0" />
          </filter>
        </entity>
      </fetch>
    </fetchxml>
    <IntroducedVersion>1.0</IntroducedVersion>
    <LocalizedNames>
      <LocalizedName description="Assignee Lookup View" languagecode="1033" />
    </LocalizedNames>
  </savedquery>
</savedqueries>